jupyterlab_todo_list/__init__.py
jupyterlab_todo_list/_version.py
jupyterlab_todo_list/handlers.py
jupyterlab_todo_list/labextension/package.json
jupyterlab_todo_list/labextension/schemas/jupyterlab-todo-list/package.json.orig
jupyterlab_todo_list/labextension/schemas/jupyterlab-todo-list/plugin.json
jupyterlab_todo_list/labextension/static/502.4c5b57fa8495b7430624.js
jupyterlab_todo_list/labextension/static/509.1f8782b0d5b2e9ee4e9e.js
jupyterlab_todo_list/labextension/static/976.95f9048a3e43690efa72.js
jupyterlab_todo_list/labextension/static/976.95f9048a3e43690efa72.js.LICENSE.txt
jupyterlab_todo_list/labextension/static/remoteEntry.edc97e0ba3c5f7a18bc4.js
jupyterlab_todo_list/labextension/static/style.js
jupyterlab_todo_list/labextension/static/third-party-licenses.json
jupyterlab_todo_list-0.2.0.data/data/share/jupyter/labextensions/jupyterlab-todo-list/package.json
jupyterlab_todo_list-0.2.0.data/data/share/jupyter/labextensions/jupyterlab-todo-list/schemas/jupyterlab-todo-list/package.json.orig
jupyterlab_todo_list-0.2.0.data/data/share/jupyter/labextensions/jupyterlab-todo-list/schemas/jupyterlab-todo-list/plugin.json
jupyterlab_todo_list-0.2.0.data/data/share/jupyter/labextensions/jupyterlab-todo-list/static/502.4c5b57fa8495b7430624.js
jupyterlab_todo_list-0.2.0.data/data/share/jupyter/labextensions/jupyterlab-todo-list/static/509.1f8782b0d5b2e9ee4e9e.js
jupyterlab_todo_list-0.2.0.data/data/share/jupyter/labextensions/jupyterlab-todo-list/static/976.95f9048a3e43690efa72.js
jupyterlab_todo_list-0.2.0.data/data/share/jupyter/labextensions/jupyterlab-todo-list/static/976.95f9048a3e43690efa72.js.LICENSE.txt
jupyterlab_todo_list-0.2.0.data/data/share/jupyter/labextensions/jupyterlab-todo-list/static/remoteEntry.edc97e0ba3c5f7a18bc4.js
jupyterlab_todo_list-0.2.0.data/data/share/jupyter/labextensions/jupyterlab-todo-list/static/style.js
jupyterlab_todo_list-0.2.0.data/data/share/jupyter/labextensions/jupyterlab-todo-list/static/third-party-licenses.json
jupyterlab_todo_list-0.2.0.dist-info/METADATA
jupyterlab_todo_list-0.2.0.dist-info/WHEEL
jupyterlab_todo_list-0.2.0.dist-info/licenses/LICENSE
jupyterlab_todo_list-0.2.0.dist-info/RECORD
