Metadata-Version: 2.4
Name: jupyterlab_todo_list
Version: 0.2.0
Summary: A JupyterLab side panel for to-dos with checkbox import from notebooks.
Project-URL: Homepage, https://github.com/xlt208/jupyterlab-todo-list
Project-URL: Bug Tracker, https://github.com/xlt208/jupyterlab-todo-list/issues
Project-URL: Repository, https://github.com/xlt208/jupyterlab-todo-list.git
Author-email: xlt208 <lingtao.xie0@gmail.com>
License: BSD 3-Clause License
License-File: LICENSE
Keywords: jupyter,jupyterlab,jupyterlab-extension
Classifier: Framework :: Jupyter
Classifier: Framework :: Jupyter :: JupyterLab
Classifier: Framework :: Jupyter :: JupyterLab :: 4
Classifier: Framework :: Jupyter :: JupyterLab :: Extensions
Classifier: Framework :: Jupyter :: JupyterLab :: Extensions :: Prebuilt
Classifier: License :: OSI Approved :: BSD License
Classifier: Programming Language :: Python
Classifier: Programming Language :: Python :: 3
Classifier: Programming Language :: Python :: 3.9
Classifier: Programming Language :: Python :: 3.10
Classifier: Programming Language :: Python :: 3.11
Classifier: Programming Language :: Python :: 3.12
Classifier: Programming Language :: Python :: 3.13
Requires-Python: >=3.9
Requires-Dist: jupyter-server>=2.0.0
